pg/__init__.py
pg/installer.py
pg/my_pip.py
pg/venv_manager.py
pg_mypip-0.1.0.dist-info/licenses/LICENSE
pg_mypip-0.1.0.dist-info/METADATA
pg_mypip-0.1.0.dist-info/WHEEL
pg_mypip-0.1.0.dist-info/entry_points.txt
pg_mypip-0.1.0.dist-info/top_level.txt
pg_mypip-0.1.0.dist-info/RECORD
