Metadata-Version: 2.4
Name: pg-mypip
Version: 0.1.0
Summary: A simple pip wrapper for virtualenv management
Author: Swetank Mishra
Requires-Python: >=3.6
License-File: LICENSE
Dynamic: author
Dynamic: license-file
Dynamic: requires-python
Dynamic: summary
